GPSDO/GPSDO.HMI.py
GPSDO/__init__.py
GPSDO/getFreq.py
GPSDO/gpsdo.py
GPSDO/gpsdont.py
GPSDO-0.1.0.dist-info/LICENSE
GPSDO-0.1.0.dist-info/METADATA
GPSDO-0.1.0.dist-info/WHEEL
GPSDO-0.1.0.dist-info/top_level.txt
GPSDO-0.1.0.dist-info/RECORD
