Metadata-Version: 2.1
Name: GPSDO
Version: 0.1.0
Summary: A GPSDO experiment
Home-page: https://www.qsl.net/zl3dw/
Author: Andrew Barron
Author-email: zl3dw@outlook.co.nz
Classifier: Programming Language :: Python
Classifier: Programming Language :: Python :: 3
Classifier: Programming Language :: Python :: 3.9
Requires-Python: >=3.6
License-File: LICENSE
